<?xml version="1.0" encoding="utf-8" ?><dwsync><file name="about-rtl.min.css" server="purgeorsplurge.com" local="3549759374" remote="3543087780" Dst="2" /><file name="about-rtl.css" server="purgeorsplurge.com" local="3549759374" remote="3543087780" Dst="2" /><file name="about.css" server="purgeorsplurge.com" local="3549759374" remote="3543087780" Dst="2" /><file name="admin-menu-rtl.css" server="purgeorsplurge.com" local="3549759374" remote="3538745040" Dst="2" /><file name="admin-menu-rtl.min.css" server="purgeorsplurge.com" local="3549759374" remote="3538745040" Dst="2" /><file name="about.min.css" server="purgeorsplurge.com" local="3549759374" remote="3543087780" Dst="2" /><file name="admin-menu.css" server="purgeorsplurge.com" local="3549759374" remote="3538745040" Dst="2" /><file name="admin-menu.min.css" server="purgeorsplurge.com" local="3549759374" remote="3538745040" Dst="2" /><file name="color-picker-rtl.css" server="purgeorsplurge.com" local="3549759374" remote="3540390660" Dst="2" /><file name="color-picker.css" server="purgeorsplurge.com" local="3549759374" remote="3540390660" Dst="2" /><file name="color-picker-rtl.min.css" server="purgeorsplurge.com" local="3549759374" remote="3540390660" Dst="2" /><file name="color-picker.min.css" server="purgeorsplurge.com" local="3549759374" remote="3540390660" Dst="2" /><file name="common-rtl.min.css" server="purgeorsplurge.com" local="3549759378" remote="3541598040" Dst="2" /><file name="common.css" server="purgeorsplurge.com" local="3549759378" remote="3541598040" Dst="2" /><file name="common-rtl.css" server="purgeorsplurge.com" local="3549759378" remote="3541598040" Dst="2" /><file name="common.min.css" server="purgeorsplurge.com" local="3549759378" remote="3541598040" Dst="2" /><file name="customize-controls-rtl.css" server="purgeorsplurge.com" local="3549759378" remote="3541528380" Dst="2" /><file name="customize-controls-rtl.min.css" server="purgeorsplurge.com" local="3549759378" remote="3541528380" Dst="2" /><file name="customize-controls.css" server="purgeorsplurge.com" local="3549759378" remote="3541528380" Dst="2" /><file name="customize-controls.min.css" server="purgeorsplurge.com" local="3549759379" remote="3541528380" Dst="2" /><file name="customize-nav-menus-rtl.css" server="purgeorsplurge.com" local="3549759379" remote="3542208900" Dst="2" /><file name="customize-nav-menus.css" server="purgeorsplurge.com" local="3549759379" remote="3542208900" Dst="2" /><file name="customize-nav-menus.min.css" server="purgeorsplurge.com" local="3549759380" remote="3542208900" Dst="2" /><file name="customize-nav-menus-rtl.min.css" server="purgeorsplurge.com" local="3549759379" remote="3542208900" Dst="2" /><file name="customize-widgets-rtl.css" server="purgeorsplurge.com" local="3549759380" remote="3540483840" Dst="2" /><file name="customize-widgets-rtl.min.css" server="purgeorsplurge.com" local="3549759380" remote="3540483840" Dst="2" /><file name="customize-widgets.css" server="purgeorsplurge.com" local="3549759380" remote="3540483840" Dst="2" /><file name="dashboard-rtl.min.css" server="purgeorsplurge.com" local="3549759380" remote="3540390660" Dst="2" /><file name="dashboard-rtl.css" server="purgeorsplurge.com" local="3549759380" remote="3540390660" Dst="2" /><file name="customize-widgets.min.css" server="purgeorsplurge.com" local="3549759380" remote="3540483840" Dst="2" /><file name="deprecated-media-rtl.css" server="purgeorsplurge.com" local="3549759380" remote="3540390660" Dst="2" /><file name="dashboard.min.css" server="purgeorsplurge.com" local="3549759380" remote="3540390660" Dst="2" /><file name="dashboard.css" server="purgeorsplurge.com" local="3549759380" remote="3540390660" Dst="2" /><file name="deprecated-media-rtl.min.css" server="purgeorsplurge.com" local="3549759380" remote="3540390660" Dst="2" /><file name="deprecated-media.css" server="purgeorsplurge.com" local="3549759380" remote="3540390660" Dst="2" /><file name="deprecated-media.min.css" server="purgeorsplurge.com" local="3549759380" remote="3540390660" Dst="2" /><file name="edit-rtl.min.css" server="purgeorsplurge.com" local="3549759381" remote="3542736900" Dst="2" /><file name="edit.css" server="purgeorsplurge.com" local="3549759381" remote="3542736900" Dst="2" /><file name="edit-rtl.css" server="purgeorsplurge.com" local="3549759380" remote="3542736900" Dst="2" /><file name="farbtastic-rtl.css" server="purgeorsplurge.com" local="3549759381" remote="3467509200" Dst="2" /><file name="farbtastic-rtl.min.css" server="purgeorsplurge.com" local="3549759381" remote="3535948620" Dst="2" /><file name="edit.min.css" server="purgeorsplurge.com" local="3549759381" remote="3542736900" Dst="2" /><file name="farbtastic.min.css" server="purgeorsplurge.com" local="3549759381" remote="3535948620" Dst="2" /><file name="farbtastic.css" server="purgeorsplurge.com" local="3549759381" remote="3467509200" Dst="2" /><file name="forms-rtl.css" server="purgeorsplurge.com" local="3549759381" remote="3539021340" Dst="2" /><file name="forms-rtl.min.css" server="purgeorsplurge.com" local="3549759381" remote="3539021340" Dst="2" /><file name="forms.css" server="purgeorsplurge.com" local="3549759381" remote="3539021340" Dst="2" /><file name="forms.min.css" server="purgeorsplurge.com" local="3549759381" remote="3539021340" Dst="2" /><file name="ie-rtl.min.css" server="purgeorsplurge.com" local="3549759381" remote="3540390660" Dst="2" /><file name="ie.css" server="purgeorsplurge.com" local="3549759381" remote="3540390660" Dst="2" /><file name="ie-rtl.css" server="purgeorsplurge.com" local="3549759381" remote="3540390660" Dst="2" /><file name="ie.min.css" server="purgeorsplurge.com" local="3549759381" remote="3540390660" Dst="2" /><file name="install-rtl.css" server="purgeorsplurge.com" local="3549759381" remote="3540390660" Dst="2" /><file name="install-rtl.min.css" server="purgeorsplurge.com" local="3549759382" remote="3540390660" Dst="2" /><file name="l10n-rtl.css" server="purgeorsplurge.com" local="3549759382" remote="3530754000" Dst="2" /><file name="install.css" server="purgeorsplurge.com" local="3549759382" remote="3540390660" Dst="2" /><file name="install.min.css" server="purgeorsplurge.com" local="3549759382" remote="3540390660" Dst="2" /><file name="l10n.min.css" server="purgeorsplurge.com" local="3549759382" remote="3535948620" Dst="2" /><file name="l10n.css" server="purgeorsplurge.com" local="3549759382" remote="3530754000" Dst="2" /><file name="l10n-rtl.min.css" server="purgeorsplurge.com" local="3549759382" remote="3535948620" Dst="2" /><file name="list-tables-rtl.min.css" server="purgeorsplurge.com" local="3549759382" remote="3540483840" Dst="2" /><file name="list-tables.css" server="purgeorsplurge.com" local="3549759382" remote="3540483840" Dst="2" /><file name="list-tables-rtl.css" server="purgeorsplurge.com" local="3549759382" remote="3540483840" Dst="2" /><file name="list-tables.min.css" server="purgeorsplurge.com" local="3549759382" remote="3540483840" Dst="2" /><file name="login-rtl.css" server="purgeorsplurge.com" local="3549759382" remote="3536603520" Dst="2" /><file name="login.css" server="purgeorsplurge.com" local="3549759382" remote="3536603520" Dst="2" /><file name="login-rtl.min.css" server="purgeorsplurge.com" local="3549759382" remote="3539021340" Dst="2" /><file name="login.min.css" server="purgeorsplurge.com" local="3549759382" remote="3539021340" Dst="2" /><file name="media-rtl.min.css" server="purgeorsplurge.com" local="3549759383" remote="3540390660" Dst="2" /><file name="media-rtl.css" server="purgeorsplurge.com" local="3549759383" remote="3540390660" Dst="2" /><file name="media.css" server="purgeorsplurge.com" local="3549759383" remote="3540390660" Dst="2" /><file name="media.min.css" server="purgeorsplurge.com" local="3549759383" remote="3540390660" Dst="2" /><file name="nav-menus-rtl.css" server="purgeorsplurge.com" local="3549759383" remote="3540390660" Dst="2" /><file name="nav-menus-rtl.min.css" server="purgeorsplurge.com" local="3549759383" remote="3540390660" Dst="2" /><file name="press-this-editor-rtl.css" server="purgeorsplurge.com" local="3549759383" remote="3520987200" Dst="2" /><file name="nav-menus.min.css" server="purgeorsplurge.com" local="3549759383" remote="3540390660" Dst="2" /><file name="nav-menus.css" server="purgeorsplurge.com" local="3549759383" remote="3540390660" Dst="2" /><file name="press-this-editor-rtl.min.css" server="purgeorsplurge.com" local="3549759383" remote="3535948620" Dst="2" /><file name="press-this-editor.css" server="purgeorsplurge.com" local="3549759383" remote="3520987200" Dst="2" /><file name="press-this-editor.min.css" server="purgeorsplurge.com" local="3549759383" remote="3535948620" Dst="2" /><file name="press-this-rtl.css" server="purgeorsplurge.com" local="3549759383" remote="3540390660" Dst="2" /><file name="press-this-rtl.min.css" server="purgeorsplurge.com" local="3549759383" remote="3539961060" Dst="2" /><file name="press-this.css" server="purgeorsplurge.com" local="3549759384" remote="3540390660" Dst="2" /><file name="press-this.min.css" server="purgeorsplurge.com" local="3549759384" remote="3539961060" Dst="2" /><file name="revisions-rtl.css" server="purgeorsplurge.com" local="3549759384" remote="3538672200" Dst="2" /><file name="revisions-rtl.min.css" server="purgeorsplurge.com" local="3549759384" remote="3538672200" Dst="2" /><file name="revisions.css" server="purgeorsplurge.com" local="3549759384" remote="3538672200" Dst="2" /><file name="revisions.min.css" server="purgeorsplurge.com" local="3549759384" remote="3538672200" Dst="2" /><file name="site-icon-rtl.min.css" server="purgeorsplurge.com" local="3549759384" remote="3540395940" Dst="2" /><file name="site-icon-rtl.css" server="purgeorsplurge.com" local="3549759384" remote="3540395940" Dst="2" /><file name="site-icon.css" server="purgeorsplurge.com" local="3549759384" remote="3540395940" Dst="2" /><file name="themes-rtl.css" server="purgeorsplurge.com" local="3549759384" remote="3543933240" Dst="2" /><file name="themes-rtl.min.css" server="purgeorsplurge.com" local="3549759384" remote="3543933240" Dst="2" /><file name="site-icon.min.css" server="purgeorsplurge.com" local="3549759384" remote="3540395940" Dst="2" /><file name="widgets-rtl.css" server="purgeorsplurge.com" local="3549759384" remote="3538745040" Dst="2" /><file name="themes.min.css" server="purgeorsplurge.com" local="3549759384" remote="3543933240" Dst="2" /><file name="themes.css" server="purgeorsplurge.com" local="3549759384" remote="3543933240" Dst="2" /><file name="widgets-rtl.min.css" server="purgeorsplurge.com" local="3549759384" remote="3538745040" Dst="2" /><file name="widgets.css" server="purgeorsplurge.com" local="3549759385" remote="3538745040" Dst="2" /><file name="wp-admin-rtl.css" server="purgeorsplurge.com" local="3549759385" remote="3518395200" Dst="2" /><file name="wp-admin-rtl.min.css" server="purgeorsplurge.com" local="3549759385" remote="3535948620" Dst="2" /><file name="widgets.min.css" server="purgeorsplurge.com" local="3549759385" remote="3538745040" Dst="2" /><file name="wp-admin.css" server="purgeorsplurge.com" local="3549759385" remote="3518395200" Dst="2" /><file name="wp-admin.min.css" server="purgeorsplurge.com" local="3549759385" remote="3535948620" Dst="2" /></dwsync>